Workbook

Sheet Legenda
A1: BuddyKids — Matrice di Test
A2: Guida alla compilazione della colonna Esito
A4: Colonna | B4: Significato
A5: Esito = OK | B5: Il test e stato eseguito e il comportamento corrisponde al risultato atteso.
A6: Esito = BUG | B6: Il comportamento non corrisponde a quanto previsto per un errore tecnico (crash, dato sbagliato, funzione che non risponde). Genera automaticamente un ID 'BUG-TC-xxx' in colonna ID Anomalia.
A7: Esito = FUNCTIONAL | B7: Il comportamento e quello atteso OGGI, ma manca un requisito/funzionalita non ancora costruita (non e un errore, e un gap di scope). Genera automaticamente un ID 'FUNCTIONAL-TC-xxx'.
A8: Esito = DA TESTARE | B8: Non ancora verificato sul deploy reale — da compilare durante il test.
A9: Priorita | B9: Alta = blocca un flusso centrale (registrazione, prenotazione, pagamento simulato, sicurezza ruoli). Media = funzionalita secondaria ma visibile. Bassa = rifinitura/nice-to-have.
A10: Task collegato | B10: Riferimento al numero di task interno gia tracciato in questa conversazione, quando applicabile.
A11: Note | B11: Ipotesi/diagnosi gia note dal codice sorgente (utile per non re-investigare da zero) o dettagli aggiuntivi.
A13: Ordine di test consigliato
A14: 1. Setup — crea le tre utenze (genitore, gestore, admin) prima di tutto il resto.
A15: 2. Genitori — Home, Cerca, Attivita, Prenotazione.
A16: 3. Genitori — Gruppi (crea gruppo, invita una seconda utenza genitore reale per testare davvero l'adesione multi-famiglia) e Accompagnamento.
A17: 4. Gestore — ricevi e rispondi alla Richiesta Gruppo generata al punto 3.
A18: 5. Gestore — Attivita/Promozioni/Profilo centro.
A19: 6. Admin — Dashboard/Gestione/Analytics/Richieste Gruppo/Tag.
A20: 7. Multi-tenant/PWA — per ultimo, richiede i tre alias/domini pubblicati.

Sheet Test Case
A1: ID Test | B1: Area | C1: Scenario | D1: Precondizioni | E1: Passi | F1: Risultato atteso | G1: Esito | H1: ID Anomalia | I1: Priorita | J1: Task collegato | K1: STATO ANOMALIA | L1: Note
A2: TC-001 | B2: Setup | C2: Registrazione nuovo account genitore | D2: Nessun account con quella email | E2: Vai su /auth/login -> tab 'Registrati' -> inserisci email+password (min 6 caratteri) -> invia | F2: Messaggio 'Controlla la tua email per confermare la registrazione'; riga creata in public.profiles con role='parent' | G2: OK | H2: =IF(G2="BUG","BUG-"&A2,IF(G2="FUNCTIONAL","FUNCTIONAL-"&A2,"")) | I2: Alta | K2: FIX (messaggio post-registrazione già mostrato in pagina, verificato nel codice) / NON-CODICE (dominio email invio - vedi task #53, azione su dashboard Supabase, non da codice) | L2: 1) Dopo aver inserito email e password, la pagina dovrebbe aggiornarsi mentre rimane sul login 2) la mail, ora, arriva da supabase: segnarsi di sistemare tutte le mail con indirizzi e domini corretti
A3: TC-002 | B3: Setup | C3: Conferma email e primo accesso | D3: Registrazione completata (TC precedente) | E3: Apri il link di conferma ricevuto via email -> verifica redirect su /auth/callback -> poi login con email+password | F3: Login riuscito, redirect a '/' | G3: OK | H3: =IF(G3="BUG","BUG-"&A3,IF(G3="FUNCTIONAL","FUNCTIONAL-"&A3,"")) | I3: Alta
A4: TC-003 | B4: Setup | C4: Login con credenziali errate | D4: Account esistente | E4: Vai su /auth/login -> inserisci password sbagliata -> invia | F4: Messaggio di errore visibile, nessun accesso | G4: BUG | H4: =IF(G4="BUG","BUG-"&A4,IF(G4="FUNCTIONAL","FUNCTIONAL-"&A4,"")) -> BUG-TC-003 | I4: Media | K4: TO DEPLOY (fixato in questa sessione: messaggi di errore login tradotti in italiano) | RISOLTO: bug label email/password non associate, vedi Note | RISOLTO (hardening test) | L4: Viene mostrato messaggio "Invalid login credentials" - inserire messaggio parlante user friendly | Bug trovato nella prima esecuzione reale della suite: le label Email/Password in LoginForm.tsx non erano associate (mancava htmlFor/id) agli input, quindi getByLabel() non trovava mai i campi e ogni test con login reale andava in timeout — causa di ~70 fallimenti in un solo run. Corretto aggiungendo htmlFor/id a Email, Password e Codice invito in LoginForm.tsx. | RUN REALE: fallimento sporadico su mobile-chrome (messaggio non trovato entro 10s) — probabile rate limit Supabase Auth (molti login paralleli, fullyParallel:true) invece del messaggio 'non corrette'. Regex del test ampliata per coprire anche 'troppi tentativi', timeout alzato a 15s.
A5: TC-004 | B5: Setup | C5: Password dimenticata | D5: Nessuna | E5: Click su 'Password dimenticata?' in /auth/login | F5: Dovrebbe avviare un flusso di reset password | G5: FUNCTIONAL | H5: =IF(G5="BUG","BUG-"&A5,IF(G5="FUNCTIONAL","FUNCTIONAL-"&A5,"")) -> FUNCTIONAL-TC-004 | I5: Bassa | J5: #11 area affine | K5: TO DEPLOY (fixato in questa sessione: reset password reale via Supabase) | L5: Noto: badge ComingSoon, nessuna azione reale implementata
A6: TC-005 | B6: Setup | C6: Promozione account a Gestore centro | D6: Account genitore registrato, accesso allo SQL Editor Supabase | E6: Esegui: update public.profiles set role='center_admin', center_id=(select id from centers where slug='...') where email='...' | F6: Il profilo ha role=center_admin e center_id valorizzato | G6: DA TESTARE | H6: =IF(G6="BUG","BUG-"&A6,IF(G6="FUNCTIONAL","FUNCTIONAL-"&A6,"")) | I6: Alta | K6: PARZIALE: TO DEPLOY (branding pagina login + CTA logout fixati) / NOT CLEAR (creazione account self-service senza SQL - task #44, serve tua decisione su workflow di approvazione) | L6: Test case tecnico - da riformulare con processo "utente" senza accesso ai db o conoscenza dell'infrastruttura tecnica Bisogna prevedere creazione account separata da quella del genitore, sono processi e flussi distinti. Anche l'homepage di autenticazione deve riportare colori e layout dell'app "Partner" e non come ora, quella dei genitori. Modificare CTA "Torna all'app" con "Esci dall'account" o simile.
A7: TC-006 | B7: Setup | C7: Login Gestore su dominio partner/alias | D7: Account promosso (TC precedente) | E7: Vai sull'alias/dominio partner -> login -> verifica redirect a /center | F7: Accesso alla dashboard Gestore, sidebar con Dashboard/Il mio centro/Attivita/Promozioni/Richieste Gruppo | G7: DA TESTARE | H7: =IF(G7="BUG","BUG-"&A7,IF(G7="FUNCTIONAL","FUNCTIONAL-"&A7,"")) | I7: Alta | J7: #6 | K7: TO DEPLOY (fixato: login tenant-aware, redirect corretto)
A8: TC-007 | B8: Setup | C8: Promozione account ad Admin piattaforma | D8: Account genitore registrato | E8: Esegui: update public.profiles set role='platform_admin' where email='...' | F8: Il profilo ha role=platform_admin | G8: DA TESTARE | H8: =IF(G8="BUG","BUG-"&A8,IF(G8="FUNCTIONAL","FUNCTIONAL-"&A8,"")) | I8: Alta | K8: PARZIALE: TO DEPLOY (branding pagina login + CTA logout fixati) / NOT CLEAR (creazione account self-service senza SQL - task #44, serve tua decisione) | L8: Test case tecnico - da riformulare con processo "utente" senza accesso ai db o conoscenza dell'infrastruttura tecnica Bisogna prevedere creazione account separata da quella del genitore, sono processi e flussi distinti. Anche l'homepage di autenticazione deve riportare colori e layout dell'app "Admin" e non come ora, quella dei genitori. Modificare CTA "Torna all'app" con "Esci dall'account" o simile
A9: TC-008 | B9: Setup | C9: Login Admin su dominio admin/alias | D9: Account promosso (TC precedente) | E9: Vai sull'alias/dominio admin -> login -> verifica redirect a /admin | F9: Accesso alla dashboard Admin | G9: DA TESTARE | H9: =IF(G9="BUG","BUG-"&A9,IF(G9="FUNCTIONAL","FUNCTIONAL-"&A9,"")) | I9: Alta | J9: #8 | K9: TO DEPLOY (fixato: login tenant-aware, redirect corretto)
A10: TC-009 | B10: Setup | C10: Accesso negato a /center con ruolo parent | D10: Account con role=parent | E10: Vai sul dominio partner e prova ad accedere | F10: Se non loggato: redirect a login sullo stesso host; se loggato come parent: redirect al dominio principale | G10: DA TESTARE | H10: =IF(G10="BUG","BUG-"&A10,IF(G10="FUNCTIONAL","FUNCTIONAL-"&A10,"")) | I10: Alta | K10: NOT CLEAR (nota è sulla riformulazione del test, non un bug applicativo - legato a #44) | L10: Test case tecnico - da riformulare con processo "utente" senza accesso ai db o conoscenza dell'infrastruttura tecnica
A11: TC-010 | B11: Setup | C11: Accesso negato a /admin con ruolo center_admin | D11: Account con role=center_admin | E11: Vai sul dominio admin e prova ad accedere | F11: Redirect al dominio principale (l'admin e' superset, il gestore no) | G11: DA TESTARE | H11: =IF(G11="BUG","BUG-"&A11,IF(G11="FUNCTIONAL","FUNCTIONAL-"&A11,"")) | I11: Alta | K11: NOT CLEAR (nota è sulla riformulazione del test, non un bug applicativo - legato a #44) | L11: Test case tecnico - da riformulare con processo "utente" senza accesso ai db o conoscenza dell'infrastruttura tecnica
A12: TC-011 | B12: Setup | C12: Logout | D12: Utente loggato (qualsiasi ruolo) | E12: Vai su Profilo (genitore) o link in sidebar (gestore/admin) -> click 'Esci' | F12: Sessione terminata, redirect a login o home pubblica | G12: DA TESTARE | H12: =IF(G12="BUG","BUG-"&A12,IF(G12="FUNCTIONAL","FUNCTIONAL-"&A12,"")) | I12: Media
A13: TC-012 | B13: Genitori - Home | C13: Home mostra attivita reali | D13: Almeno un'attivita inserita in Supabase | E13: Login come genitore -> apri '/' | F13: Le card 'Popolari' mostrano attivita reali dal DB, non i dati demo | G13: FUNCTIONAL | H13: =IF(G13="BUG","BUG-"&A13,IF(G13="FUNCTIONAL","FUNCTIONAL-"&A13,"")) -> FUNCTIONAL-TC-012 | I13: Alta | J13: #3 | K13: PARZIALE: TO DEPLOY (ordinamento interim su rating/recensioni reali fixato) / NOT CLEAR (definizione di business di cosa rende un'attività "Popolare" - serve tua decisione) | L13: Inserire TC per creazione - lato Partner - dell'attività. Specificare funzionalmente come deve essere resa "Popolare" una attività
A14: TC-013 | B14: Genitori - Home | C14: Filtro categoria in Home | D14: Nessuna | E14: Su Home, clicca una categoria (es. Sport) -> poi 'Tutte' | F14: Le card mostrate cambiano in base al tag selezionato; 'Tutte' ripristina la lista intera | G14: BUG | H14: =IF(G14="BUG","BUG-"&A14,IF(G14="FUNCTIONAL","FUNCTIONAL-"&A14,"")) -> BUG-TC-013 | I14: Alta | J14: #30 | K14: AGGIORNATO: la vecchia UI Home "Popolari vicino a te" con filtro categoria e stata sostituita dal toggle Planner/Per bambino; test riscritto per verificare il chip Sport dentro Per bambino > Categorie (vedi HomeFeed.tsx / PerBambinoView.tsx). | RISOLTO | L14: BUG DI TEST TROVATO+CORRETTO (run reale): la regex /border-sky/ matchava anche la classe statica 'hover:border-sky' presente nel chip NON selezionato (CategoryChip.tsx), quindi l'assert 'non selezionato' falliva sempre. Corretta con lookbehind negativo (?<!hover:)border-sky\b.
A15: TC-014 | B15: Genitori - Home | C15: Geolocalizzazione Home | D15: Permessi posizione del browser concessi | E15: Clicca 'Attivita sulla mappa' / 'Usa posizione' -> concedi permesso | F15: Il testo mostra un conteggio reale di centri entro 5 km (non piu fisso a 24) | G15: ENHANCEMENT | H15: =IF(G15="BUG","BUG-"&A15,IF(G15="FUNCTIONAL","FUNCTIONAL-"&A15,"")) | I15: Media | J15: #30 | K15: TO DEPLOY (fixato: la posizione rilevata resta salvata tra Home e Cerca in questa sessione) | L15: La geolocalizzazione funziona, ma ogni volta riappare la CTA "Usa posizione" dopo qualsiasi passaggio. Bisogna rivedere la UX
A16: TC-015 | B16: Genitori - Home | C16: Geolocalizzazione negata | D16: Nessuna | E16: Clicca 'Usa posizione' -> nega il permesso | F16: Messaggio di errore leggibile, l'app non si blocca | G16: ENHANCEMENT | H16: =IF(G16="BUG","BUG-"&A16,IF(G16="FUNCTIONAL","FUNCTIONAL-"&A16,"")) | I16: Bassa | K16: PARZIALE: TO DEPLOY (messaggio di errore migliorato) / NOT CLEAR (il browser blocca la ri-richiesta del popup nativo dopo un rifiuto per policy di sicurezza - limite del browser, non risolvibile lato app) | L16: Funziona: "Non è stato possibile ottenre la posizione - controlla i permessi" e la CTA rimane "Usa la posizione". Se possibile deve riapparire il pop-up di chrome per richiedere accesso ai dati di geolocalizzazione
A17: TC-016 | B17: Genitori - Cerca | C17: Ricerca testuale | D17: Nessuna | E17: Vai su /search -> digita il nome di un'attivita esistente | F17: Solo le attivita corrispondenti restano in lista | G17: BUG | H17: =IF(G17="BUG","BUG-"&A17,IF(G17="FUNCTIONAL","FUNCTIONAL-"&A17,"")) -> BUG-TC-016 | I17: Alta | K17: TO DEPLOY (Azzera ora sempre visibile; azzeramento per singolo filtro non ancora implementato - solo azzeramento globale) | RISOLTO | L17: Funziona. Manca - su tutti i filtri - la possibilità di cancellare il filtro applicato | BUG DI TEST TROVATO+CORRETTO (run reale): l'assert finale era invertita (.not.toHaveText invece di .toHaveText) — svuotare la ricerca deve ripristinare lo STESSO conteggio iniziale, non uno diverso.
A18: TC-017 | B18: Genitori - Cerca | C18: Filtro Eta | D18: Nessuna | E18: Apri filtro 'Eta' -> sposta gli slider min/max | F18: La lista si aggiorna mostrando solo attivita compatibili con la fascia | G18: ENHANCEMENT | H18: =IF(G18="BUG","BUG-"&A18,IF(G18="FUNCTIONAL","FUNCTIONAL-"&A18,"")) | I18: Media | J18: #31 | K18: TO DEPLOY (fixato: due campi numerici da/a al posto degli slider sovrapposti) | L18: Funziona: rivedrei solo l'UX della selezione della fascia d'età che non è facilmente comprensibile. Forse unica striscia con pallino di età minima e pallino di età massima? O anche campo testuale? Manca - su tutti i filtri - la possibilità di cancellare il filtro applicato
A19: TC-018 | B19: Genitori - Cerca | C19: Filtro Prezzo | D19: Nessuna | E19: Apri filtro 'Prezzo' -> abbassa il tetto massimo | F19: Scompaiono le attivita piu costose del tetto | G19: OK | H19: =IF(G19="BUG","BUG-"&A19,IF(G19="FUNCTIONAL","FUNCTIONAL-"&A19,"")) | I19: Media | J19: #31 | K19: TO DEPLOY (Azzera ora sempre visibile; azzeramento per singolo filtro non ancora implementato) | L19: Funziona. Manca - su tutti i filtri - la possibilità di cancellare il filtro applicato
A20: TC-019 | B20: Genitori - Cerca | C20: Filtro Zona (testo) | D20: Nessuna | E20: Apri filtro 'Zona' -> digita una via/quartiere presente in un indirizzo | F20: Restano solo le attivita con quell'indirizzo/centro | G20: ENHANCEMENT | H20: =IF(G20="BUG","BUG-"&A20,IF(G20="FUNCTIONAL","FUNCTIONAL-"&A20,"")) | I20: Media | J20: #31 | K20: TO DEPLOY (fixato: autocomplete zona con sole vie/zone/comuni, esclusi nomi di centri/attività) | L20: Funziona. La ricerca per "Zona" deve avere una lista di comuni, quartieri, zone che si autocompilano Manca - su tutti i filtri - la possibilità di cancellare il filtro applicato
A21: TC-020 | B21: Genitori - Cerca | C21: Filtro Servizi - Bar | D21: Almeno un centro con 'Bar' attivato nel profilo | E21: Apri filtro 'Servizi' -> seleziona 'Bar nel centro' | F21: Restano solo le attivita di centri con has_bar=true | G21: OK | H21: =IF(G21="BUG","BUG-"&A21,IF(G21="FUNCTIONAL","FUNCTIONAL-"&A21,"")) | I21: Alta | J21: #31 | K21: TO DEPLOY (Azzera ora sempre visibile; azzeramento per singolo filtro non ancora implementato) | L21: Funziona. Manca - su tutti i filtri - la possibilità di cancellare il filtro applicato
A22: TC-021 | B22: Genitori - Cerca | C22: Filtro Servizi - Pranzo/Pre/Post | D22: Nessuna | E22: Seleziona singolarmente Pranzo incluso / Pre-scuola / Post-scuola | F22: La lista si filtra coerentemente con i campi dell'attivita | G22: ENHANCEMENT | H22: =IF(G22="BUG","BUG-"&A22,IF(G22="FUNCTIONAL","FUNCTIONAL-"&A22,"")) | I22: Media | J22: #31 | K22: TO DEPLOY (fixato: sezione Servizi disponibili nel dettaglio attività) | L22: Funziona. Nella scheda di dettaglio dell'attività devono essere mostrati in maniera chiara sintetica e veloce i servizi disponibili altrimenti non c'è modo di avere conferma della selezione corretta
A23: TC-022 | B23: Genitori - Cerca | C23: Azzeramento filtri | D23: Uno o piu filtri attivi | E23: Clicca 'Azzera (N)' | F23: Tutti i filtri tornano al default e il pulsante scompare | G23: ENHANCEMENT | H23: =IF(G23="BUG","BUG-"&A23,IF(G23="FUNCTIONAL","FUNCTIONAL-"&A23,"")) | I23: Bassa | K23: TO DEPLOY (fixato: Azzera sempre visibile e chiude anche il pannello aperto) | L23: Funziona. La CTA "Azzera" deve essere visibile sempre - e una volta cliccata deve riportare allo staot iniziale la pagina "Cerca" (nel test fatto, avevo il tab "Servizi" esploso, ed è rimasto aperto anche dopo "azzera")
A24: TC-023 | B24: Genitori - Cerca | C24: Ricerca con geolocalizzazione da Home | D24: Aver cliccato 'Usa posizione' in Home | E24: Da Home, dopo la geolocalizzazione, clicca 'Vedi in Cerca' | F24: Si apre /search?lat=..&lng=.. con distanze reali calcolate e badge 'Vicino a te' | G24: BUG | H24: =IF(G24="BUG","BUG-"&A24,IF(G24="FUNCTIONAL","FUNCTIONAL-"&A24,"")) -> BUG-TC-023 | I24: Media | J24: #30 | K24: PARZIALE: TO DEPLOY (raggio filtro coerente Home->Cerca, coordinate rilevate ora visibili) / DA COSTRUIRE (mappa reale con pin spostabile - task #51, sbloccata: scelto Leaflet/OSM gratuito, ancora da costruire) | L24: Cliccando sulla CTA "Vedi in cerca" sembra perdersi il filtro sulla geolocalizzazione (prima mi dava in home 0 centri - giusto - poi riappaiono tutti in "Cerca"). Deve rimanere attivo il filtro geo applicato. Da rendere visibile anche il punto di geolocalizzazione in alto alla lista, in modo da controllare se è corretto. La mappa deve dare la possibilità di spostare il PIN qualora sia posizionato in modo sbagliato
A25: TC-024 | B25: Genitori - Cerca | C25: Filtro Date | D25: Nessuna | E25: Clicca il chip 'Date' | F25: Dovrebbe aprire un filtro per data/settimana | G25: DA TESTARE | H25: =IF(G25="BUG","BUG-"&A25,IF(G25="FUNCTIONAL","FUNCTIONAL-"&A25,"")) | I25: Bassa | K25: RISOLTO | L25: NOT CLEAR risolto con decisione di Fabrizio: il filtro Date ora seleziona una delle 13 settimane stagionali e filtra i risultati a chi ha REALMENTE posti liberi in quell'intervallo (activity_weeks.spots_left > 0), non solo un'etichetta ComingSoon. Pre-applicato anche arrivando dal Planner con ?week= (vedi TC-158).
A26: TC-025 | B26: Genitori - Attivita | C26: Apertura scheda attivita | D26: Nessuna | E26: Da Home o Cerca, clicca una card | F26: Si apre /activity/[slug] con dati reali (prezzo, eta, descrizione, tag) | H26: =IF(G26="BUG","BUG-"&A26,IF(G26="FUNCTIONAL","FUNCTIONAL-"&A26,"")) | I26: Alta
A27: TC-026 | B27: Genitori - Attivita | C27: Preferiti (cuore) | D27: Nessuna | E27: Sulla card o nel dettaglio, clicca l'icona cuore, poi ricarica la pagina | F27: Lo stato del preferito dovrebbe restare salvato dopo il reload | G27: BUG | H27: =IF(G27="BUG","BUG-"&A27,IF(G27="FUNCTIONAL","FUNCTIONAL-"&A27,"")) -> BUG-TC-026 | I27: Alta | J27: #21 | K27: DA COSTRUIRE (task #21, V1 - non ancora iniziato) | RISOLTO | L27: Noto: torna sempre allo stato iniziale al reload (solo useState locale, non salvato) | BUG DI TEST TROVATO+CORRETTO (run reale): DetailClient.tsx inizializza il preferito con useState(true) (parte sempre pieno), non useState(false) come assunto — dopo reload torna pieno, non vuoto. Test corretto per riflettere il comportamento reale (il gap di persistenza resta, ma il valore di default e' 'preferito').
A28: TC-027 | B28: Genitori - Attivita | C28: Recensioni | D28: Attivita con prenotazioni concluse | E28: Apri il dettaglio di un'attivita | F28: Ci si aspetta di vedere eventuali recensioni reali dei genitori | G28: FUNCTIONAL | H28: =IF(G28="BUG","BUG-"&A28,IF(G28="FUNCTIONAL","FUNCTIONAL-"&A28,"")) -> FUNCTIONAL-TC-027 | I28: Media | J28: #13 | K28: DA COSTRUIRE (task #13, V1 - non ancora iniziato) | L28: Noto: sezione recensioni sempre vuota, non ancora collegata a dati reali
A29: TC-028 | B29: Genitori - Attivita | C29: Promozioni attive visibili | D29: Il gestore ha creato una promozione attiva | E29: Apri il dettaglio dell'attivita promozionata | F29: Il badge/sconto della promozione e visibile ai genitori | H29: =IF(G29="BUG","BUG-"&A29,IF(G29="FUNCTIONAL","FUNCTIONAL-"&A29,"")) | I29: Media
A30: TC-029 | B30: Genitori - Prenotazione | C30: Prenotazione completa | D30: Attivita con settimane disponibili, almeno un bambino inserito | E30: Apri attivita -> 'Prenota' -> step 1 scegli settimane -> step 2 scegli bambino/i -> step 3 scegli pagamento -> conferma | F30: Prenotazione creata in Supabase (bookings/booking_weeks/booking_kids), redirect a schermata di successo | H30: =IF(G30="BUG","BUG-"&A30,IF(G30="FUNCTIONAL","FUNCTIONAL-"&A30,"")) | I30: Alta
A31: TC-030 | B31: Genitori - Prenotazione | C31: Sconto multi-settimana | D31: Prenotazione con 2+ settimane selezionate | E31: Seleziona 2 o piu settimane nello step 1 | F31: Il totale mostra la riga 'Sconto multi-settimana' -5% calcolata sul subtotale (settimane x prezzo x bambini) | H31: =IF(G31="BUG","BUG-"&A31,IF(G31="FUNCTIONAL","FUNCTIONAL-"&A31,"")) | I31: Media | J31: #36
A32: TC-031 | B32: Genitori - Prenotazione | C32: Sconto famiglia 2+ bambini | D32: Almeno 2 bambini salvati nel profilo | E32: Nello step 2, seleziona 2 o piu bambini per la stessa prenotazione | F32: Il totale mostra 'Sconto famiglia' pari a -10% sul 2 bambino, -15% sul 3, -20% dal 4 in poi (rispetto al prezzo pieno di un bambino); il subtotale e moltiplicato per il numero di bambini selezionati | H32: =IF(G32="BUG","BUG-"&A32,IF(G32="FUNCTIONAL","FUNCTIONAL-"&A32,"")) | I32: Alta | J32: #36 | L32: Feature nuova: verificare anche che si sommi correttamente allo sconto multi-settimana (vedi tema aperto sulla cumulabilita)
A33: TC-032 | B33: Genitori - Prenotazione | C33: Aggiunta bambino durante la prenotazione | D33: Nessun bambino ancora salvato | E33: Nello step 2, clicca 'Aggiungi bambino' e compila il form | F33: Il bambino viene salvato e selezionabile subito, il totale si aggiorna | H33: =IF(G33="BUG","BUG-"&A33,IF(G33="FUNCTIONAL","FUNCTIONAL-"&A33,"")) | I33: Media
A34: TC-033 | B34: Genitori - Prenotazione | C34: Pagamento (simulato) | D34: Prenotazione in corso, step 3 | E34: Scegli un metodo di pagamento e conferma | F34: Testo esplicito 'Pagamento simulato a scopo dimostrativo' nella schermata di successo, nessun addebito reale | G34: OK | H34: =IF(G34="BUG","BUG-"&A34,IF(G34="FUNCTIONAL","FUNCTIONAL-"&A34,"")) | I34: Alta | J34: #14 | L34: Atteso in questa fase: i pagamenti reali sono pianificati come ultimo step
A35: TC-034 | B35: Genitori - Prenotazione | C35: Rimando ad Andiamo Insieme nello step prenotazione | D35: Nessuna | E35: Nello step 2 di prenotazione, osserva la sezione 'Andiamo Insieme' | F35: Badge ComingSoon visibile | G35: FUNCTIONAL | H35: =IF(G35="BUG","BUG-"&A35,IF(G35="FUNCTIONAL","FUNCTIONAL-"&A35,"")) -> FUNCTIONAL-TC-034 | I35: Bassa | K35: NOT CLEAR (valutare se rimuovere/rimandare al gruppo - decisione di design, non urgente) | L35: Valutare se rimandare direttamente alla pagina Gruppo ora che l'Accompagnamento esiste li
A36: TC-035 | B36: Genitori - Gruppi | C36: Creazione gruppo | D36: Login genitore | E36: Vai su /groups -> '+ Nuovo' -> inserisci nome -> 'Crea gruppo' | F36: Il gruppo appare nella lista 'I miei gruppi', utente aggiunto come primo membro | G36: BUG | H36: =IF(G36="BUG","BUG-"&A36,IF(G36="FUNCTIONAL","FUNCTIONAL-"&A36,"")) -> BUG-TC-035 | I36: Alta | K36: RISOLTO | L36: Bug trovato durante l'automazione test: il test Playwright navigava su /groups senza sessione autenticata (un TODO diceva di aggiungere il login ma non era mai stato fatto), quindi il pulsante '+ Nuovo' non compariva mai (timeout). Corretto aggiungendo loginAs(page, 'parent') prima della navigazione in tests/genitori/gruppi.spec.ts.
A37: TC-036 | B37: Genitori - Gruppi | C37: Apertura dettaglio gruppo | D37: Gruppo creato | E37: Clicca sulla card del gruppo ('Apri gruppo') | F37: Si apre /groups/[id] con nome, pulsante Invita famiglie, tab Bambini&Richiesta e Accompagnamento | H37: =IF(G37="BUG","BUG-"&A37,IF(G37="FUNCTIONAL","FUNCTIONAL-"&A37,"")) | I37: Alta
A38: TC-037 | B38: Genitori - Gruppi | C38: Collegamento attivita al gruppo | D38: Sei il creatore del gruppo, nessuna attivita ancora collegata | E38: Nella pagina gruppo, 'Scegli attivita' -> seleziona dalla lista -> 'Conferma' | F38: L'header del gruppo mostra il nome attivita e centro collegati | H38: =IF(G38="BUG","BUG-"&A38,IF(G38="FUNCTIONAL","FUNCTIONAL-"&A38,"")) | I38: Alta
A39: TC-038 | B39: Genitori - Gruppi | C39: Invito ad altre famiglie | D39: Gruppo creato | E39: Click 'Invita famiglie' -> condividi o copia il link generato (/groups/join/[id]) | F39: Il link viene copiato/condiviso correttamente; su mobile con Web Share API si apre il menu di condivisione nativo | H39: =IF(G39="BUG","BUG-"&A39,IF(G39="FUNCTIONAL","FUNCTIONAL-"&A39,"")) | I39: Alta | L39: Feature nuova, verificare anche il messaggio 'Link copiato!' quando non c'e Web Share API
A40: TC-039 | B40: Genitori - Gruppi | C40: Adesione a un gruppo tramite link di invito | D40: Link di invito valido, secondo account genitore | E40: Apri il link /groups/join/[id] da un altro account (loggato) -> click 'Unisciti al gruppo' | F40: L'utente diventa membro del gruppo e viene reindirizzato a /groups/[id] con accesso completo | H40: =IF(G40="BUG","BUG-"&A40,IF(G40="FUNCTIONAL","FUNCTIONAL-"&A40,"")) | I40: Alta
A41: TC-040 | B41: Genitori - Gruppi | C41: Adesione a un gruppo gia membro | D41: Utente gia membro del gruppo | E41: Riapri lo stesso link di invito e clicca 'Unisciti' | F41: Nessun errore: l'azione riconosce che sei gia membro (alreadyMember) e prosegue | H41: =IF(G41="BUG","BUG-"&A41,IF(G41="FUNCTIONAL","FUNCTIONAL-"&A41,"")) | I41: Media
A42: TC-041 | B42: Genitori - Gruppi | C42: Aggiunta bambino con preferenza | D42: Hai almeno un bambino salvato nel tuo profilo | E42: In 'Bambini iscritti', clicca '+ Aggiungi' -> scegli bambino -> scegli una preferenza (tag) -> eventuali note -> 'Aggiungi bambino' | F42: Il bambino compare subito nella lista con la preferenza indicata (la pagina si aggiorna da sola); il contatore si aggiorna | H42: =IF(G42="BUG","BUG-"&A42,IF(G42="FUNCTIONAL","FUNCTIONAL-"&A42,"")) | I42: Alta | L42: Verificare che dopo il salvataggio la UI si aggiorni senza bisogno di refresh manuale (bug corretto)
A43: TC-042 | B43: Genitori - Gruppi | C43: Tentativo di aggiungere due volte lo stesso bambino | D43: Bambino gia iscritto al gruppo | E43: Prova ad aggiungere di nuovo lo stesso bambino allo stesso gruppo | F43: Messaggio chiaro 'Questo bambino e gia iscritto a questo gruppo' invece dell'errore tecnico del database | H43: =IF(G43="BUG","BUG-"&A43,IF(G43="FUNCTIONAL","FUNCTIONAL-"&A43,"")) | I43: Media
A44: TC-043 | B44: Genitori - Gruppi | C44: Rimozione proprio bambino dal gruppo | D44: Bambino tuo gia iscritto | E44: Clicca la X accanto al bambino | F44: Il bambino sparisce dalla lista, contatore aggiornato | H44: =IF(G44="BUG","BUG-"&A44,IF(G44="FUNCTIONAL","FUNCTIONAL-"&A44,"")) | I44: Media
A45: TC-044 | B45: Genitori - Gruppi | C45: Bambini di altri genitori - privacy | D45: Un secondo genitore ha aggiunto un suo bambino allo stesso gruppo | E45: Osserva la lista bambini iscritti | F45: Il bambino di un'altra famiglia compare come 'Bambino/a' generico con la sua preferenza, MAI il nome reale | H45: =IF(G45="BUG","BUG-"&A45,IF(G45="FUNCTIONAL","FUNCTIONAL-"&A45,"")) | I45: Alta | L45: Verifica di sicurezza/privacy intenzionale
A46: TC-045 | B46: Genitori - Gruppi | C46: Generazione aggregazioni | D46: Almeno 2 bambini con preferenze diverse iscritti | E46: Clicca 'Genera aggregazioni' | F46: Compaiono sotto-gruppi per ciascuna preferenza (es. Calcio, Danza) con conteggio bambini e badge di compatibilita col campo | H46: =IF(G46="BUG","BUG-"&A46,IF(G46="FUNCTIONAL","FUNCTIONAL-"&A46,"")) | I46: Alta
A47: TC-046 | B47: Genitori - Gruppi | C47: Aggregazione non compatibile | D47: Un'attivita collegata che NON ha il tag scelto da un bambino | E47: Genera le aggregazioni | F47: Il sotto-gruppo con quella preferenza mostra badge 'Non disponibile in questo campo' | H47: =IF(G47="BUG","BUG-"&A47,IF(G47="FUNCTIONAL","FUNCTIONAL-"&A47,"")) | I47: Media
A48: TC-047 | B48: Genitori - Gruppi | C48: Rigenerazione aggregazioni | D48: Aggregazioni gia generate, poi bambini aggiunti/rimossi | E48: Clicca di nuovo 'Genera aggregazioni' | F48: I sotto-gruppi precedenti vengono sostituiti (non duplicati) con quelli aggiornati | H48: =IF(G48="BUG","BUG-"&A48,IF(G48="FUNCTIONAL","FUNCTIONAL-"&A48,"")) | I48: Media
A49: TC-048 | B49: Genitori - Gruppi | C49: Anteprima sconto Richiesta Gruppo | D49: Gruppo con N bambini iscritti | E49: Osserva il riquadro sconto nella sezione 'Richiesta Gruppo' | F49: Mostra la percentuale corretta secondo le fasce (5+ kids: 5%, 8+: 10%, 12+: 15%) | H49: =IF(G49="BUG","BUG-"&A49,IF(G49="FUNCTIONAL","FUNCTIONAL-"&A49,"")) | I49: Alta
A50: TC-049 | B50: Genitori - Gruppi | C50: Invio Richiesta Gruppo | D50: Attivita collegata, almeno 1 bambino iscritto | E50: Scrivi un messaggio (opzionale) -> 'Invia Richiesta Gruppo' | F50: La richiesta appare come 'In attesa'; il box si sostituisce col riepilogo della richiesta inviata | H50: =IF(G50="BUG","BUG-"&A50,IF(G50="FUNCTIONAL","FUNCTIONAL-"&A50,"")) | I50: Alta
A51: TC-050 | B51: Genitori - Gruppi | C51: Aggregazioni con bambini di famiglie diverse | D51: Due account genitore diversi, entrambi membri dello stesso gruppo (tramite invito), ciascuno con almeno un bambino iscritto con preferenze diverse | E51: Da un secondo account genitore reale, unisciti al gruppo tramite link di invito e aggiungi un tuo bambino con una preferenza diversa da quella gia presente -> torna sull'account del creatore -> clicca 'Genera aggregazioni' | F51: Le aggregazioni includono ANCHE il bambino della seconda famiglia (non solo i propri), raggruppato correttamente per preferenza; il bambino della seconda famiglia compare come 'Bambino/a' generico (privacy) ma viene conteggiato nel sotto-gruppo giusto | H51: =IF(G51="BUG","BUG-"&A51,IF(G51="FUNCTIONAL","FUNCTIONAL-"&A51,"")) | I51: Alta | L51: Verifica esplicita richiesta da Fabrizio - analisi statica del codice suggerisce che funzioni (generateSubgroupsAction filtra solo per group_id, non per parent_id), ma va confermato con un test reale a due utenze prima di darlo per buono
A52: TC-051 | B52: Genitori - Gruppi | C52: Richiesta Gruppo senza attivita collegata | D52: Gruppo senza attivita | E52: Prova a inviare una Richiesta Gruppo | F52: Messaggio di errore 'Collega prima un'attivita al gruppo' | H52: =IF(G52="BUG","BUG-"&A52,IF(G52="FUNCTIONAL","FUNCTIONAL-"&A52,"")) | I52: Media
A53: TC-052 | B53: Gestore - Richieste Gruppo | C53: Ricezione Richiesta Gruppo lato Gestore | D53: Richiesta inviata verso un centro gestito da un account center_admin | E53: Login Gestore -> 'Richieste Gruppo' | F53: La richiesta compare in 'In attesa' con nome gruppo, attivita, numero bambini, sconto proposto | H53: =IF(G53="BUG","BUG-"&A53,IF(G53="FUNCTIONAL","FUNCTIONAL-"&A53,"")) | I53: Alta
A54: TC-053 | B54: Gestore - Richieste Gruppo | C54: Accetta/Rifiuta Richiesta Gruppo | D54: Richiesta in attesa | E54: Click 'Accetta' (o 'Rifiuta') | F54: La richiesta si sposta in 'Storico' con lo stato corretto; il genitore vede lo stesso stato aggiornato nella pagina gruppo | H54: =IF(G54="BUG","BUG-"&A54,IF(G54="FUNCTIONAL","FUNCTIONAL-"&A54,"")) | I54: Alta
A55: TC-054 | B55: Gestore - Richieste Gruppo | C55: Vedi solo le richieste del proprio centro | D55: Piu centri con richieste diverse | E55: Apri /center/group-requests con un account collegato a un solo centro | F55: Vedi solo le richieste dirette al proprio centro, non quelle di altri centri | H55: =IF(G55="BUG","BUG-"&A55,IF(G55="FUNCTIONAL","FUNCTIONAL-"&A55,"")) | I55: Alta | L55: Verifica sicurezza RLS
A56: TC-055 | B56: Gestore - Richieste Gruppo | C56: Storico richieste | D56: Richieste gia accettate/rifiutate | E56: Scorri la sezione 'Storico' | F56: Mostra tutte le richieste risolte con lo stato corretto | H56: =IF(G56="BUG","BUG-"&A56,IF(G56="FUNCTIONAL","FUNCTIONAL-"&A56,"")) | I56: Bassa
A57: TC-056 | B57: Genitori - Accompagnamento | C57: Proporsi come autista | D57: Nella pagina gruppo, tab Accompagnamento | E57: Inserisci posti disponibili, seggiolini, tratta -> 'Proponi un passaggio' | F57: L'offerta compare in 'Tutte le offerte nel gruppo' | H57: =IF(G57="BUG","BUG-"&A57,IF(G57="FUNCTIONAL","FUNCTIONAL-"&A57,"")) | I57: Alta
A58: TC-057 | B58: Genitori - Accompagnamento | C58: Aggiornare la propria offerta | D58: Offerta gia creata | E58: Cambia i valori -> 'Aggiorna offerta' | F58: I valori si aggiornano (upsert, non duplica righe) | H58: =IF(G58="BUG","BUG-"&A58,IF(G58="FUNCTIONAL","FUNCTIONAL-"&A58,"")) | I58: Media
A59: TC-058 | B59: Genitori - Accompagnamento | C59: Rimuovere la propria offerta | D59: Offerta esistente | E59: Click 'Rimuovi' | F59: L'offerta sparisce dalla lista | H59: =IF(G59="BUG","BUG-"&A59,IF(G59="FUNCTIONAL","FUNCTIONAL-"&A59,"")) | I59: Media
A60: TC-059 | B60: Genitori - Accompagnamento | C60: Richiedere un passaggio | D60: Nella tab Accompagnamento | E60: Inserisci n. bambini, seggiolino richiesto, tratta -> 'Richiedi un passaggio' | F60: La sezione 'Abbinamenti proposti per te' appare | H60: =IF(G60="BUG","BUG-"&A60,IF(G60="FUNCTIONAL","FUNCTIONAL-"&A60,"")) | I60: Alta
A61: TC-060 | B61: Genitori - Accompagnamento | C61: Abbinamento compatibile | D61: Un'offerta con stessa tratta (o entrambe), posti sufficienti, seggiolino se richiesto | E61: Dopo aver creato la richiesta, guarda 'Abbinamenti proposti per te' | F61: L'offerta compatibile compare nella lista | H61: =IF(G61="BUG","BUG-"&A61,IF(G61="FUNCTIONAL","FUNCTIONAL-"&A61,"")) | I61: Alta
A62: TC-061 | B62: Genitori - Accompagnamento | C62: Abbinamento filtrato per seggiolino | D62: Richiesta con seggiolino richiesto attivo, offerta senza seggiolino | E62: Controlla abbinamenti | F62: L'offerta senza seggiolino NON deve comparire | H62: =IF(G62="BUG","BUG-"&A62,IF(G62="FUNCTIONAL","FUNCTIONAL-"&A62,"")) | I62: Alta | L62: Verifica logica di matching (lib/carpool.ts)
A63: TC-062 | B63: Genitori - Accompagnamento | C63: Abbinamento filtrato per tratta | D63: Richiesta con tratta 'Ritorno', offerta con tratta 'Andata' | E63: Controlla abbinamenti | F63: L'offerta 'solo andata' non deve comparire tra i risultati per il ritorno | H63: =IF(G63="BUG","BUG-"&A63,IF(G63="FUNCTIONAL","FUNCTIONAL-"&A63,"")) | I63: Alta
A64: TC-063 | B64: Genitori - Accompagnamento | C64: Nessun abbinamento disponibile | D64: Richiesta creata, nessuna offerta compatibile | E64: Controlla 'Abbinamenti proposti per te' | F64: Messaggio 'Nessun abbinamento compatibile ancora' | H64: =IF(G64="BUG","BUG-"&A64,IF(G64="FUNCTIONAL","FUNCTIONAL-"&A64,"")) | I64: Bassa
A65: TC-064 | B65: Genitori - Calendario | C65: Calendario personale | D65: Bambino con prenotazione confermata | E65: Vai su /calendar | F65: Gli eventi mostrati riflettono le prenotazioni reali | H65: =IF(G65="BUG","BUG-"&A65,IF(G65="FUNCTIONAL","FUNCTIONAL-"&A65,"")) | I65: Alta | J65: #4
A66: TC-065 | B66: Genitori - Calendario | C66: Giorni evidenziati calendario centro | D66: Prenotazione con giorni specifici frequentati | E66: Apri tab 'Calendari centri' | F66: I giorni effettivamente prenotati dovrebbero essere evidenziati | G66: FUNCTIONAL | H66: =IF(G66="BUG","BUG-"&A66,IF(G66="FUNCTIONAL","FUNCTIONAL-"&A66,"")) -> FUNCTIONAL-TC-065 | I66: Media | J66: #22 | K66: DA COSTRUIRE (task #22, V1 - confermato da tuo commento sul roadmap Word: "questo lo sistemerei") | L66: Noto: bookedDays/eventDays arrivano ancora da dati demo, non riflettono la prenotazione reale
A67: TC-066 | B67: Genitori - Profilo | C67: Visualizza profilo | D67: Login genitore | E67: Vai su /profile | F67: Nome/email reali, lista bambini reale | H67: =IF(G67="BUG","BUG-"&A67,IF(G67="FUNCTIONAL","FUNCTIONAL-"&A67,"")) | I67: Alta
A68: TC-067 | B68: Genitori - Profilo | C68: Aggiungere un bambino | D68: Nessuna | E68: '+ Aggiungi' nella sezione bambini -> compila nome/eta/altro -> salva | F68: Il bambino compare nella lista, salvato su Supabase | H68: =IF(G68="BUG","BUG-"&A68,IF(G68="FUNCTIONAL","FUNCTIONAL-"&A68,"")) | I68: Alta
A69: TC-068 | B69: Genitori - Profilo | C69: Statistiche profilo | D69: Nessuna | E69: Osserva i 3 riquadri statistici in alto (Prenotazioni/Gruppi/Risparmiati) | F69: Dovrebbero riflettere i dati reali dell'utente | G69: FUNCTIONAL | H69: =IF(G69="BUG","BUG-"&A69,IF(G69="FUNCTIONAL","FUNCTIONAL-"&A69,"")) -> FUNCTIONAL-TC-068 | I69: Bassa | K69: DA COSTRUIRE (task #16, V1 - non ancora iniziato) | L69: Noto: numeri fissi demo (12/3/85 euro), badge 'Numeri demo' visibile
A70: TC-069 | B70: Genitori - Profilo | C70: Modifica profilo | D70: Nessuna | E70: Click 'Modifica' accanto al nome | F70: Dovrebbe aprire un form di modifica dati | G70: FUNCTIONAL | H70: =IF(G70="BUG","BUG-"&A70,IF(G70="FUNCTIONAL","FUNCTIONAL-"&A70,"")) -> FUNCTIONAL-TC-069 | I70: Bassa | K70: DA COSTRUIRE (V2 - release successiva) | L70: Noto: badge ComingSoon, nessuna azione | AGGIORNATO: il form 'Modifica' ora include anche telefono, data di nascita e genere (vedi TC-132), non solo nome/ruolo.
A71: TC-070 | B71: Genitori - Profilo | C71: Voci menu in arrivo | D71: Nessuna | E71: Osserva 'Le mie prenotazioni', 'Notifiche', 'Preferiti', 'Navetta', 'Chat con organizzatori', 'Ricevute e fatture', 'Lingua' | F71: Tutte mostrano badge ComingSoon, nessuna e cliccabile in modo funzionale | G71: FUNCTIONAL | H71: =IF(G71="BUG","BUG-"&A71,IF(G71="FUNCTIONAL","FUNCTIONAL-"&A71,"")) -> FUNCTIONAL-TC-070 | I71: Bassa | J71: #20/#21/#15 | K71: DA COSTRUIRE (mix V1/V2 - legato a #20/#21/#15, vedi roadmap) | L71: Ogni voce corrisponde a un task gia tracciato | AGGIORNATO: 'Notifiche' e 'Lingua' non sono piu' placeholder ComingSoon in questo elenco Attivita' — sono state sostituite dalla sezione 'Preferenze' reale (lingua/tema/notifiche, vedi TC-134) e 'Sicurezza'/'Privacy e account' (vedi TC-133,135,136,137). Le voci ComingSoon rimaste in questa lista sono solo: Le mie prenotazioni, Preferiti, Navetta, Chat con organizzatori, Ricevute e fatture. | AGGIORNATO ULTERIORE: 'Notifiche' e' ora un link reale (non piu' un'assenza da verificare) verso /profile/notifiche, dentro il menu 'Impostazioni' con Metodi di pagamento aggiunto come nuova voce ComingSoon.
A72: TC-071 | B72: Genitori - Profilo | C72: Logout da Profilo | D72: Login attivo | E72: Click 'Esci' in fondo alla pagina | F72: Sessione terminata | H72: =IF(G72="BUG","BUG-"&A72,IF(G72="FUNCTIONAL","FUNCTIONAL-"&A72,"")) | I72: Media
A73: TC-072 | B73: Gestore - Dashboard | C73: Dashboard Gestore | D73: Login Gestore centro | E73: Apri /center | F73: KPI, grafico occupazione, prenotazioni recenti e 'Le tue attivita' dovrebbero riflettere il centro reale | G73: BUG | H73: =IF(G73="BUG","BUG-"&A73,IF(G73="FUNCTIONAL","FUNCTIONAL-"&A73,"")) -> BUG-TC-072 | I73: Alta | J73: #19 | K73: VOLUTAMENTE DEMO (nota tua sul roadmap Word: sezione da tenere demo per presentazione ai partner - task #19) | AGGIORNAMENTO: redesign dashboard implementato in questa sessione (task #92, layout approvato 6a) — vedi TC-119/120/121; KPI/banner/feed ora aggregano più fonti reali (settimane scariche, richieste gruppo, prenotazioni) ma con alcuni timestamp sintetici nel feed; resta comunque "volutamente demo" per presentazione partner come da tua indicazione originale. | RISOLTO | L73: Noto: mostra sempre dati mock, mai quelli reali del centro collegato | BUG DI TEST TROVATO+CORRETTO (run reale): getByText('Attivita',{exact:true}) andava in strict-mode violation (4 elementi: link sidebar, pillola nav mobile, card KPI, intestazione tabella — sidebar e pillola mobile sono SEMPRE nel DOM, solo nascoste via CSS in base al viewport). Scoping alla griglia KPI (.grid.grid-cols-2.gap-3).
A74: TC-073 | B74: Gestore - Attivita | C74: Elenco attivita del centro | D74: Account collegato a un centro (center_id valorizzato) | E74: Apri /center/activities | F74: Mostra solo le attivita reali di quel centro | H74: =IF(G74="BUG","BUG-"&A74,IF(G74="FUNCTIONAL","FUNCTIONAL-"&A74,"")) | I74: Alta
A75: TC-074 | B75: Gestore - Attivita | C75: Creazione nuova attivita | D75: Nessuna | E75: '+ Nuova attivita' -> compila form -> 'Crea attivita' | F75: Attivita salvata su Supabase, redirect alla pagina di modifica | H75: =IF(G75="BUG","BUG-"&A75,IF(G75="FUNCTIONAL","FUNCTIONAL-"&A75,"")) | I75: Alta
A76: TC-075 | B76: Gestore - Attivita | C76: Modifica attivita | D76: Attivita esistente | E76: Apri un'attivita -> modifica prezzo/eta/servizi/tag -> salva | F76: I dati si aggiornano su Supabase, log azione registrato | H76: =IF(G76="BUG","BUG-"&A76,IF(G76="FUNCTIONAL","FUNCTIONAL-"&A76,"")) | I76: Alta | L76: IMPLEMENTATO: apre la scheda modifica dell'attività di test e verifica due fix di coerenza UI: la nav 'Attività' resta evidenziata sulla sotto-rotta di modifica, e 'Usa posizione attuale' compila lat/lng dal browser.
A77: TC-076 | B77: Gestore - Attivita | C77: Calendario disponibilita giorno-per-giorno | D77: Attivita esistente | E77: Apri 'Calendario' dell'attivita -> apri/chiudi giorni, aggiorna posti, giornata speciale -> salva | F77: I dati si aggiornano su activity_days | H77: =IF(G77="BUG","BUG-"&A77,IF(G77="FUNCTIONAL","FUNCTIONAL-"&A77,"")) | I77: Media
A78: TC-077 | B78: Gestore - Attivita | C78: Nessun centro collegato all'account | D78: Account center_admin senza center_id valorizzato | E78: Apri /center/activities o /center/activities/new | F78: Messaggio chiaro che serve completare l'assegnazione via SQL, nessun crash | H78: =IF(G78="BUG","BUG-"&A78,IF(G78="FUNCTIONAL","FUNCTIONAL-"&A78,"")) | I78: Media
A79: TC-078 | B79: Gestore - Promozioni | C79: Creazione promozione | D79: Attivita esistente | E79: Vai su /center/promotions -> crea promo (sconto giorno fisso o last-minute) | F79: Promozione salvata, visibile ai genitori nel dettaglio attivita | H79: =IF(G79="BUG","BUG-"&A79,IF(G79="FUNCTIONAL","FUNCTIONAL-"&A79,"")) | I79: Media
A80: TC-079 | B80: Gestore - Promozioni | C80: Attiva/disattiva promozione | D80: Promozione esistente | E80: Toggle attivo/non attivo | F80: Stato aggiornato su Supabase | H80: =IF(G80="BUG","BUG-"&A80,IF(G80="FUNCTIONAL","FUNCTIONAL-"&A80,"")) | I80: Bassa
A81: TC-080 | B81: Gestore - Profilo Centro | C81: Modifica profilo centro | D81: Account collegato a un centro | E81: Vai su /center/profile -> modifica nome/citta/descrizione/social -> salva | F81: Dati aggiornati, visibili ai genitori | H81: =IF(G81="BUG","BUG-"&A81,IF(G81="FUNCTIONAL","FUNCTIONAL-"&A81,"")) | I81: Media
A82: TC-081 | B82: Gestore - Profilo Centro | C82: Attivazione campo Bar | D82: Nessuna | E82: In /center/profile, spunta 'Il centro ha un bar / punto ristoro' -> salva | F82: Il valore has_bar=true si riflette nel filtro Servizi lato genitori | H82: =IF(G82="BUG","BUG-"&A82,IF(G82="FUNCTIONAL","FUNCTIONAL-"&A82,"")) | I82: Alta
A83: TC-082 | B83: Admin - Dashboard | C83: Dashboard Admin | D83: Login platform_admin | E83: Apri /admin | F83: KPI, occupazione, prenotazioni recenti e lista centri dovrebbero riflettere i dati reali | G83: FUNCTIONAL | H83: =IF(G83="BUG","BUG-"&A83,IF(G83="FUNCTIONAL","FUNCTIONAL-"&A83,"")) -> FUNCTIONAL-TC-082 | I83: Alta | J83: #19 | K83: VOLUTAMENTE DEMO (task #19) | L83: Noto: mostra sempre dati mock
A84: TC-083 | B84: Admin - Gestione | C84: Elenco attivita (tutte) | D84: Nessuna | E84: Apri /admin/activities | F84: Dovrebbe riflettere le attivita reali create dai gestori | G84: FUNCTIONAL | H84: =IF(G84="BUG","BUG-"&A84,IF(G84="FUNCTIONAL","FUNCTIONAL-"&A84,"")) -> FUNCTIONAL-TC-083 | I84: Media | J84: #19 | K84: VOLUTAMENTE DEMO (task #19) | L84: Noto: dati mock
A85: TC-084 | B85: Admin - Gestione | C85: Elenco prenotazioni (tutte) | D85: Nessuna | E85: Apri /admin/bookings | F85: Dovrebbe riflettere le prenotazioni reali | G85: FUNCTIONAL | H85: =IF(G85="BUG","BUG-"&A85,IF(G85="FUNCTIONAL","FUNCTIONAL-"&A85,"")) -> FUNCTIONAL-TC-084 | I85: Media | J85: #19 | K85: VOLUTAMENTE DEMO (task #19) | L85: Noto: dati mock
A86: TC-085 | B86: Admin - Gestione | C86: Elenco centri | D86: Nessuna | E86: Apri /admin/centers | F86: Dovrebbe riflettere i centri reali (salvo il form 'Nuovo centro' che e reale) | G86: FUNCTIONAL | H86: =IF(G86="BUG","BUG-"&A86,IF(G86="FUNCTIONAL","FUNCTIONAL-"&A86,"")) -> FUNCTIONAL-TC-085 | I86: Media | J86: #19 | K86: VOLUTAMENTE DEMO (task #19) | L86: Noto: lista mock
A87: TC-086 | B87: Admin - Gestione | C87: Creazione nuovo centro | D87: Nessuna | E87: Su /admin/centers, usa il form 'Nuovo centro' -> compila -> salva | F87: Il centro viene creato su Supabase | H87: =IF(G87="BUG","BUG-"&A87,IF(G87="FUNCTIONAL","FUNCTIONAL-"&A87,"")) | I87: Alta
A88: TC-087 | B88: Admin - Gestione | C88: Dettaglio centro | D88: Centro esistente | E88: Apri /admin/centers/[id] | F88: Dovrebbe mostrare i dati reali del centro | G88: FUNCTIONAL | H88: =IF(G88="BUG","BUG-"&A88,IF(G88="FUNCTIONAL","FUNCTIONAL-"&A88,"")) -> FUNCTIONAL-TC-087 | I88: Bassa | J88: #19 | K88: VOLUTAMENTE DEMO (task #19) | L88: Noto: dati mock
A89: TC-088 | B89: Admin - Gestione | C89: Gestione tag piattaforma | D89: Nessuna | E89: Apri /admin/tags -> crea/modifica un tag (es. 'Nuoto sincronizzato') | F89: Il tag e subito selezionabile dai gestori nelle attivita E dai genitori come preferenza gruppo | H89: =IF(G89="BUG","BUG-"&A89,IF(G89="FUNCTIONAL","FUNCTIONAL-"&A89,"")) | I89: Alta
A90: TC-089 | B90: Admin - Richieste Gruppo | C90: Report Richieste Gruppo multi-centro | D90: Richieste create su piu centri diversi | E90: Apri /admin/group-requests | F90: Tabella con TUTTE le richieste di tutti i centri (gruppo, attivita, centro, bambini, sconto, stato, data), sola lettura, con contatori in alto | H90: =IF(G90="BUG","BUG-"&A90,IF(G90="FUNCTIONAL","FUNCTIONAL-"&A90,"")) | I90: Alta | L90: Feature nuova
A91: TC-090 | B91: Admin - Analytics | C91: Tabella attivita Gestori | D91: Almeno un gestore ha modificato qualcosa | E91: Apri /admin/analytics | F91: La tabella 'Attivita dei Gestori centro' mostra dati reali (activity_log) | H91: =IF(G91="BUG","BUG-"&A91,IF(G91="FUNCTIONAL","FUNCTIONAL-"&A91,"")) | I91: Alta
A92: TC-091 | B92: Admin - Analytics | C92: Grafici occupazione/categorie/eta | D92: Nessuna | E92: Osserva i grafici sotto la tabella | F92: Dovrebbero riflettere le attivita reali | G92: FUNCTIONAL | H92: =IF(G92="BUG","BUG-"&A92,IF(G92="FUNCTIONAL","FUNCTIONAL-"&A92,"")) -> FUNCTIONAL-TC-091 | I92: Media | J92: #23 | K92: VOLUTAMENTE DEMO (task #23) | L92: Noto: calcolati sempre sui dati mock
A93: TC-092 | B93: Admin - Analytics | C93: Centri limitrofi complementari | D93: Nessuna | E93: Osserva la sezione in fondo alla pagina Analytics | F93: Dovrebbe riflettere i centri reali | G93: FUNCTIONAL | H93: =IF(G93="BUG","BUG-"&A93,IF(G93="FUNCTIONAL","FUNCTIONAL-"&A93,"")) -> FUNCTIONAL-TC-092 | I93: Bassa | J93: #23 | K93: VOLUTAMENTE DEMO (task #23) | L93: Noto: sempre calcolata sui centri mock
A94: TC-093 | B94: Multi-tenant / PWA | C94: Routing per sottodominio/alias | D94: I tre alias .vercel.app configurati | E94: Apri i tre alias (family/partner/admin) | F94: Ognuno mostra l'app corretta senza login incrociato | H94: =IF(G94="BUG","BUG-"&A94,IF(G94="FUNCTIONAL","FUNCTIONAL-"&A94,"")) | I94: Alta
A95: TC-094 | B95: Multi-tenant / PWA | C95: Manifest PWA per tenant | D95: Nessuna | E95: DevTools -> Application -> Manifest su ciascun alias | F95: Nome, icone e colori corretti per il tenant, nessun errore 'No manifest detected' | H95: =IF(G95="BUG","BUG-"&A95,IF(G95="FUNCTIONAL","FUNCTIONAL-"&A95,"")) | I95: Alta
A96: TC-095 | B96: Multi-tenant / PWA | C96: Installazione PWA Android | D96: Chrome Android | E96: Verifica banner 'Installa' su ciascuna delle tre app | F96: Installazione riuscita, icona corretta in home screen | H96: =IF(G96="BUG","BUG-"&A96,IF(G96="FUNCTIONAL","FUNCTIONAL-"&A96,"")) | I96: Alta
A97: TC-096 | B97: Multi-tenant / PWA | C97: Login separato per alias .vercel.app | D97: Login gia fatto su un alias | E97: Apri un secondo alias | F97: Richiede login separato (cookie non condiviso tra .vercel.app diversi) | G97: OK | H97: =IF(G97="BUG","BUG-"&A97,IF(G97="FUNCTIONAL","FUNCTIONAL-"&A97,"")) | I97: Media | L97: Comportamento noto e atteso, non un bug
A98: TC-097 | B98: Multi-tenant / PWA | C98: Barra di navigazione fissa durante lo scroll (mobile) | D98: Pagina con contenuto lungo, mobile | E98: Scorri la pagina in una qualsiasi delle 3 app | F98: La barra di navigazione/menu resta visibile (fissa in cima o in fondo) durante lo scroll | H98: =IF(G98="BUG","BUG-"&A98,IF(G98="FUNCTIONAL","FUNCTIONAL-"&A98,"")) | I98: Alta | J98: #24 | K98: TO DEPLOY (fix già fatto in sessione precedente - barra nav sticky - da riverificare sul deploy reale) | L98: Corretto in questa sessione (altezza fissa app-shell + wrapper sticky su dashboard mobile) - da riverificare sul deploy reale
A99: TC-098 | B99: Fuori scope attuale | C99: Notifiche email conferma prenotazione | D99: Prenotazione completata | E99: Controlla la casella email del genitore | F99: Dovrebbe arrivare un'email di conferma | G99: FUNCTIONAL | H99: =IF(G99="BUG","BUG-"&A99,IF(G99="FUNCTIONAL","FUNCTIONAL-"&A99,"")) -> FUNCTIONAL-TC-098 | I99: Bassa | J99: #15 | K99: DA COSTRUIRE (task #15, V1 - non ancora iniziato) | L99: Noto: nessuna email viene inviata (non implementato)
A100: TC-099 | B100: Fuori scope attuale | C100: Candidatura staff camp | D100: Nessuna | E100: Cerca una sezione 'Lavora con noi' o candidatura staff | F100: Dovrebbe esistere un flusso di candidatura | G100: FUNCTIONAL | H100: =IF(G100="BUG","BUG-"&A100,IF(G100="FUNCTIONAL","FUNCTIONAL-"&A100,"")) -> FUNCTIONAL-TC-099 | I100: Bassa | J100: #9 | K100: DA COSTRUIRE (V2 - release successiva, task #9) | L100: Noto: non presente, pianificato per fase futura
...

Sheet Riepilogo
A1: Riepilogo per Esito
A2: Esito | B2: Conteggio | D2: Area | E2: N. test
A3: OK | B3: =COUNTIF('Test Case'!G:G,"OK") -> 17 | D3: Setup | E3: =COUNTIF('Test Case'!B:B,"Setup") -> 11
A4: BUG | B4: =COUNTIF('Test Case'!G:G,"BUG") -> 12 | D4: Genitori - Home | E4: =COUNTIF('Test Case'!B:B,"Genitori - Home") -> 12
A5: FUNCTIONAL | B5: =COUNTIF('Test Case'!G:G,"FUNCTIONAL") -> 18 | D5: Genitori - Cerca | E5: =COUNTIF('Test Case'!B:B,"Genitori - Cerca") -> 12
A6: DA TESTARE | B6: =COUNTIF('Test Case'!G:G,"DA TESTARE") -> 359 | D6: Genitori - Attivita | E6: =COUNTIF('Test Case'!B:B,"Genitori - Attivita") -> 16
A7: Totale test case | B7: =COUNTA('Test Case'!A2:A10000) -> 498 | D7: Genitori - Prenotazione | E7: =COUNTIF('Test Case'!B:B,"Genitori - Prenotazione") -> 17
D8: Genitori - Gruppi | E8: =COUNTIF('Test Case'!B:B,"Genitori - Gruppi") -> 17
D9: Gestore - Richieste Gruppo | E9: =COUNTIF('Test Case'!B:B,"Gestore - Richieste Gruppo") -> 4
D10: Genitori - Accompagnamento | E10: =COUNTIF('Test Case'!B:B,"Genitori - Accompagnamento") -> 8
D11: Genitori - Calendario | E11: =COUNTIF('Test Case'!B:B,"Genitori - Calendario") -> 2
D12: Genitori - Profilo | E12: =COUNTIF('Test Case'!B:B,"Genitori - Profilo") -> 23
D13: Gestore - Dashboard | E13: =COUNTIF('Test Case'!B:B,"Gestore - Dashboard") -> 4
D14: Gestore - Attivita | E14: =COUNTIF('Test Case'!B:B,"Gestore - Attivita") -> 9
D15: Gestore - Promozioni | E15: =COUNTIF('Test Case'!B:B,"Gestore - Promozioni") -> 2
D16: Gestore - Profilo Centro | E16: =COUNTIF('Test Case'!B:B,"Gestore - Profilo Centro") -> 4
D17: Admin - Dashboard | E17: =COUNTIF('Test Case'!B:B,"Admin - Dashboard") -> 2
D18: Admin - Gestione | E18: =COUNTIF('Test Case'!B:B,"Admin - Gestione") -> 7
D19: Admin - Richieste Gruppo | E19: =COUNTIF('Test Case'!B:B,"Admin - Richieste Gruppo") -> 1
D20: Admin - Analytics | E20: =COUNTIF('Test Case'!B:B,"Admin - Analytics") -> 3
D21: Multi-tenant / PWA | E21: =COUNTIF('Test Case'!B:B,"Multi-tenant / PWA") -> 7
D22: Fuori scope attuale | E22: =COUNTIF('Test Case'!B:B,"Fuori scope attuale") -> 3
D23: Genitori - Home (Planner/Per Bambino) | E23: =COUNTIF('Test Case'!B:B,"Genitori - Home (Planner/Per Bambino)") -> 14
D24: Gestore - Inviti | E24: =COUNTIF('Test Case'!B:B,"Gestore - Inviti") -> 6
D25: Genitori - Registrazione | E25: =COUNTIF('Test Case'!B:B,"Genitori - Registrazione") -> 2
D26: Gestore - Le mie richieste | E26: =COUNTIF('Test Case'!B:B,"Gestore - Le mie richieste") -> 4
D27: Gestore - Report presenze | E27: =COUNTIF('Test Case'!B:B,"Gestore - Report presenze") -> 2
D28: Admin - Nuovi pannelli | E28: =COUNTIF('Test Case'!B:B,"Admin - Nuovi pannelli") -> 3
D29: Gestore - Account | E29: =COUNTIF('Test Case'!B:B,"Gestore - Account") -> 1
D30: Gestore - Il mio account | E30: =COUNTIF('Test Case'!B:B,"Gestore - Il mio account") -> 2
D31: Gestore - Registro presenze | E31: =COUNTIF('Test Case'!B:B,"Gestore - Registro presenze") -> 6
D32: NEXTGEN - Setup | E32: =COUNTIF('Test Case'!B:B,"NEXTGEN - Setup") -> 6
D33: NEXTGEN - Dashboard Genitore | E33: =COUNTIF('Test Case'!B:B,"NEXTGEN - Dashboard Genitore") -> 3
D34: NEXTGEN - Ricerca e scoperta | E34: =COUNTIF('Test Case'!B:B,"NEXTGEN - Ricerca e scoperta") -> 3
D35: NEXTGEN - Planner | E35: =COUNTIF('Test Case'!B:B,"NEXTGEN - Planner") -> 7
D36: NEXTGEN - Home (rifinitura) | E36: =COUNTIF('Test Case'!B:B,"NEXTGEN - Home (rifinitura)") -> 11
D37: Versione LEGACY/NEXTGEN - Toggle | E37: =COUNTIF('Test Case'!B:B,"Versione LEGACY/NEXTGEN - Toggle") -> 5
D38: NEXTGEN - Community | E38: =COUNTIF('Test Case'!B:B,"NEXTGEN - Community") -> 9
D39: TRAMA - Login | E39: =COUNTIF('Test Case'!B:B,"TRAMA - Login") -> 4
